h2hdb/__init__.py
h2hdb/__main__.py
h2hdb/compress_gallery_to_cbz.py
h2hdb/config_loader.py
h2hdb/h2hdb_h2hdb.py
h2hdb/h2hdb_spec.py
h2hdb/hash_dict.py
h2hdb/information.py
h2hdb/logger.py
h2hdb/mysql_connector.py
h2hdb/py.typed
h2hdb/settings.py
h2hdb/sql_connector.py
h2hdb/table_comments.py
h2hdb/table_database_setting.py
h2hdb/table_files_dbids.py
h2hdb/table_gids.py
h2hdb/table_removed_gids.py
h2hdb/table_tags.py
h2hdb/table_times.py
h2hdb/table_titles.py
h2hdb/table_uploadaccounts.py
h2hdb/threading_tools.py
h2hdb/view_ginfo.py
h2hdb-0.9.1.9.dist-info/licenses/LICENSE
h2hdb-0.9.1.9.dist-info/METADATA
h2hdb-0.9.1.9.dist-info/WHEEL
h2hdb-0.9.1.9.dist-info/top_level.txt
h2hdb-0.9.1.9.dist-info/RECORD
