Metadata-Version: 2.4
Name: h2hdb
Version: 0.9.1.9
Summary: A simple H@H database
Author: Kuan-Lun Wang
License: GNU Affero General Public License v3
Project-URL: Homepage, https://github.com/Kuan-Lun/h2hdb
Project-URL: Source, https://github.com/Kuan-Lun/h2hdb
Project-URL: Tracker, https://github.com/Kuan-Lun/h2hdb/issues
Classifier: Development Status :: 3 - Alpha
Classifier: Intended Audience :: Developers
Classifier: Operating System :: OS Independent
Classifier: License :: OSI Approved :: GNU Affero General Public License v3 or later (AGPLv3+)
Classifier: Programming Language :: Python :: 3.13
License-File: LICENSE
Requires-Dist: h2h-galleryinfo-parser>=0.2.2
Requires-Dist: mysql-connector-python<10.0.0,>=9.3.0
Requires-Dist: pillow<12.0.0,>=11.2.1
Requires-Dist: pydantic>=2.11.4
Dynamic: license-file
